{
  "opendb_id": "4ba10945-d6d6-40a1-b63a-c3b2c59a7fc8",
  "metadata": {
    "name": "HYTE Revolt 3 Small Form Factor Premium ITX Computer Gaming Case with 700W 80+ Gold SFX Power Supply, Black",
    "manufacturer": "HYTE",
    "part_numbers": [
      "CS-HYTE-REVOLT3-BP"
    ],
    "series": "Revolt 3",
    "variant": "Black"
  },
  "form_factor": "Mini-ITX Tower",
  "power_supply": "80+ Gold SFX-L PSU",
  "power_supply_included": true,
  "side_panel": "None",
  "has_transparent_side_panel": false,
  "front_panel_usb": "1 x USB 3.2 Gen 2 Type-C, 2 x USB 3.2 Gen 1 Type-A",
  "max_video_card_length": 335,
  "max_cpu_cooler_height": 140,
  "internal_3_5_bays": 1,
  "internal_2_5_bays": 2,
  "expansion_slots": 3,
  "dimensions": "16.10\" x 7.00\" x 9.90\"",
  "volume": 0,
  "weight": 14,
  "color": [],
  "supported_power_supply_form_factors": [],
  "front_usb_ports": [],
  "general_product_information": {
    "amazon_sku": "B0964CTPRG",
    "newegg_sku": "N82E16811736014",
    "walmart_sku": 743109943
  }
}