{
  "opendb_id": "4219c773-9d40-41ed-8173-7e6675c43629",
  "metadata": {
    "name": "be quiet! Light Wings 140mm White Addressable RGB PWM 51.37 CFM 1-Pack",
    "manufacturer": "be quiet!",
    "part_numbers": [],
    "series": "Light",
    "variant": "140mm White"
  },
  "size": 140,
  "color": [
    "WHITE"
  ],
  "quantity": 1,
  "min_airflow": 51.37,
  "max_airflow": null,
  "min_noise_level": 25.5,
  "max_noise_level": null,
  "pwm": true,
  "led": "Addressable RGB",
  "connector": "4-pin PWM + 3-pin 5V Addressable RGB",
  "controller": "None",
  "static_pressure": 1.1,
  "flow_direction": "Reverse",
  "general_product_information": {}
}