{
  "opendb_id": "96154827-9e13-4b49-bb78-e9cd8e0eaa01",
  "connectors": {
    "atx_24_pin": 1,
    "eps_8_pin": 0,
    "pcie_12vhpwr": 0,
    "pcie_6_plus_2_pin": 0,
    "sata": 6,
    "molex_4_pin": 0,
    "floppy_4_pin": 0
  },
  "metadata": {
    "name": "Corsair RM1000e (2025) White 1000W Fully Modular",
    "manufacturer": "Corsair",
    "part_numbers": [
      "CP-9020294-NA                                                    CP-9020294-AU                                                    CP-9020294-UK                                                    CP-9020294-EU"
    ],
    "series": "RM1000e",
    "variant": "1000W "
  },
  "wattage": 1000,
  "form_factor": "ATX",
  "efficiency_rating": "",
  "modular": "Full",
  "color": [
    "WHITE"
  ],
  "length": 140,
  "fanless": false,
  "general_product_information": {
    "amazon_sku": "B0DZXKYWSH",
    "newegg_sku": "N82E16817139342",
    "bestbuy_sku": 6621913
  }
}