{
  "opendb_id": "17b95d1d-e33c-41bd-b16c-f5281e4172b0",
  "cores": {
    "total": 12,
    "performance": 12,
    "threads": 24
  },
  "clocks": {
    "performance": {
      "base": 2.7,
      "boost": 3.5
    }
  },
  "cache": {
    "l2": 3,
    "l3": 30
  },
  "specifications": {
    "integratedGraphics": {
      "model": "None"
    },
    "memory": {
      "maxSupport": 0,
      "types": []
    },
    "tdp": 130,
    "eccSupport": true,
    "includesCooler": false,
    "packaging": "Boxed",
    "lithography": "22 nm",
    "simultaneousMultithreading": true
  },
  "metadata": {
    "name": "Intel Xeon E5-2697 V2 2.7 GHz 12-Core LGA2011",
    "manufacturer": "Intel",
    "part_numbers": [
      "BX80635E52697V2"
    ],
    "series": "Intel Xeon E5"
  },
  "series": "Intel Xeon E5",
  "microarchitecture": "Ivy Bridge",
  "coreFamily": "Ivy Bridge-EP",
  "socket": "LGA2011",
  "general_product_information": {
    "amazon_sku": "B00F42GWK6",
    "walmart_sku": 123162742
  }
}