{
  "opendb_id": "1917223b-ee1e-4643-b0ef-e250bca0abf8",
  "cores": {
    "total": 10,
    "performance": null,
    "efficiency": null,
    "threads": 20
  },
  "clocks": {
    "performance": {
      "base": 3.3,
      "boost": 4.2
    },
    "efficiency": {
      "base": null,
      "boost": null
    }
  },
  "cache": {
    "l1": null,
    "l2": null,
    "l3": 16.5
  },
  "specifications": {
    "integratedGraphics": {
      "model": "None",
      "baseClock": null,
      "boostClock": null,
      "shaderCount": null
    },
    "memory": {
      "maxSupport": 128,
      "types": [
        "DDR4"
      ],
      "channels": 4
    },
    "tdp": 165,
    "eccSupport": false,
    "includesCooler": false,
    "packaging": null,
    "lithography": "14 nm",
    "simultaneousMultithreading": true
  },
  "metadata": {
    "name": "Intel Core i9-9820X X-series Processor (16.5M Cache, up to 4.20 GHz)",
    "part_numbers": [],
    "releaseYear": 2018
  },
  "series": "Intel Core i9",
  "microarchitecture": "Skylake-X",
  "coreFamily": "Skylake-X",
  "socket": "LGA2066",
  "general_product_information": {
    "amazon_sku": "B07KCCH7JL",
    "newegg_sku": "9SIBMM4KBA7655"
  }
}