{
  "opendb_id": "22546c6c-9af1-4646-a9af-0ede3444c6b7",
  "cores": {
    "total": 10,
    "threads": 16
  },
  "clocks": {
    "performance": {
      "base": 2.5,
      "boost": 4.6
    },
    "efficiency": {
      "base": 1.8,
      "boost": 3.3
    }
  },
  "cache": {
    "l2": 5,
    "l3": 20
  },
  "specifications": {
    "integratedGraphics": {
      "model": "None"
    },
    "memory": {
      "maxSupport": 192,
      "types": [
        "DDR4",
        "DDR5"
      ]
    },
    "tdp": 65,
    "eccSupport": false,
    "includesCooler": true,
    "packaging": "Boxed",
    "lithography": "10 nm",
    "simultaneousMultithreading": true
  },
  "metadata": {
    "name": "Intel Core i5 13400F 2.5 GHz 10-Core LGA1700",
    "manufacturer": "Intel",
    "part_numbers": [
      "BX8071513400F"
    ],
    "series": "Intel Core i5"
  },
  "series": "Intel Core i5",
  "microarchitecture": "Raptor Lake",
  "coreFamily": "Raptor Lake",
  "socket": "LGA1700",
  "general_product_information": {
    "amazon_sku": "B0BQ6BRL4T",
    "newegg_sku": "N82E16819118431",
    "bestbuy_sku": 6530251,
    "walmart_sku": 1546920346
  }
}