{
  "opendb_id": "f34f9bc1-0136-43ee-bd78-a9efbd0e5f17",
  "cores": {
    "total": 6,
    "performance": 6,
    "threads": 12
  },
  "clocks": {
    "performance": {
      "base": 3.6,
      "boost": 4.2
    }
  },
  "cache": {
    "l2": 3,
    "l3": 32
  },
  "specifications": {
    "integratedGraphics": {
      "model": "None"
    },
    "memory": {
      "maxSupport": 128,
      "types": [
        "DDR4"
      ]
    },
    "tdp": 65,
    "eccSupport": false,
    "includesCooler": true,
    "packaging": "Boxed",
    "lithography": "7 nm",
    "simultaneousMultithreading": true
  },
  "metadata": {
    "name": "AMD Ryzen 5 3600 3.6 GHz 6-Core AM4",
    "manufacturer": "AMD",
    "part_numbers": [
      "Ryzen 5 3600                                                    100-100000031BOX"
    ],
    "series": "AMD Ryzen 5"
  },
  "series": "AMD Ryzen 5",
  "microarchitecture": "Zen 2",
  "coreFamily": "Matisse",
  "socket": "AM4",
  "general_product_information": {
    "amazon_sku": "B07STGGQ18",
    "newegg_sku": "N82E16819113569",
    "bestbuy_sku": 6356278,
    "walmart_sku": 1923977030
  }
}