{
  "opendb_id": "2c5f42bd-df61-4dea-9c4f-c20194b15b84",
  "power_connectors": {
    "pcie_6_pin": 0,
    "pcie_8_pin": 1,
    "pcie_12VHPWR": 0,
    "pcie_12V_2x6": 0
  },
  "metadata": {
    "name": "MSI GeForce RTX 2060 GAMING Z 6G",
    "manufacturer": "MSI",
    "part_numbers": [],
    "series": "GAMING Z",
    "variant": "6G",
    "releaseYear": 2019
  },
  "chipset_manufacturer": "NVIDIA",
  "chipset": "GeForce RTX 2060",
  "memory": 6,
  "memory_type": "GDDR6",
  "core_base_clock": 1530,
  "core_boost_clock": 1830,
  "effective_memory_clock": 14000,
  "memory_bus": 192,
  "interface": "PCI Express x16 3.0",
  "frame_sync": "G-SYNC™",
  "length": 247,
  "tdp": 190,
  "case_expansion_slot_width": 3,
  "total_slot_width": 3,
  "cooling": null,
  "video_outputs": {
    "hdmi_2_1": 1,
    "hdmi_2_0": 1,
    "displayport_2_1": 3,
    "displayport_2_1a": 0,
    "displayport_1_4a": 0,
    "dvi_d": 0,
    "vga": 0,
    "_id": "6778af39cda752bef3858e97"
  },
  "color": [],
  "general_product_information": {
    "amazon_sku": "B07MQ36Z6L",
    "newegg_sku": "9SIAM4SGUD4038",
    "walmart_sku": 619736797
  }
}