{
  "opendb_id": "8093bff2-3d49-4bd6-8158-bf5082b87fea",
  "power_connectors": {
    "pcie_6_pin": 0,
    "pcie_8_pin": 0,
    "pcie_12VHPWR": 0,
    "pcie_12V_2x6": 0
  },
  "metadata": {
    "name": "Asus ROG Astral Dhahab CORE OC GeForce RTX 5080 16GB GDDR7 Gold / Blue",
    "manufacturer": "Asus",
    "part_numbers": [
      "ROG-ASTRAL-RTX5080-O16G-DHAHAB-CORE"
    ],
    "series": "GeForce RTX 5080",
    "variant": "Asus"
  },
  "chipset_manufacturer": "GeForce",
  "chipset": "GeForce RTX 5080",
  "memory": 16,
  "memory_type": "GDDR7",
  "core_base_clock": 2300,
  "core_boost_clock": 2790,
  "effective_memory_clock": 30000,
  "memory_bus": 256,
  "interface": "PCIe x16",
  "color": [
    "GOLD",
    "BLUE"
  ],
  "length": 358,
  "tdp": 360,
  "total_slot_width": 4,
  "cooling": "3 Fans",
  "video_outputs": {
    "hdmi_2_1": 2,
    "hdmi_2_0": 0,
    "displayport_2_1": 3,
    "displayport_2_1a": 0,
    "displayport_1_4a": 0,
    "dvi_d": 0,
    "vga": 0,
    "_id": "688ec9a43ebf909c29b82193"
  },
  "core_count": 10752,
  "general_product_information": {}
}