{
  "opendb_id": "a97a58ca-8845-4098-9a8d-c58fd73af4fc",
  "power_connectors": {
    "pcie_6_pin": 0,
    "pcie_8_pin": 0,
    "pcie_12VHPWR": 0,
    "pcie_12V_2x6": 0
  },
  "metadata": {
    "name": "ASUS TUF Gaming GeForce RTX™ 4070 SUPER 12GB GDDR6X OC Edition",
    "manufacturer": "ASUS",
    "part_number": "DUAL-RTX4070S-O12G-EVO-WHITE",
    "series": "TUF Gaming",
    "variant": "OC Edition",
    "releaseYear": 2024,
    "part_numbers": []
  },
  "chipset_manufacturer": "NVIDIA",
  "chipset": "GeForce RTX 4070 SUPER",
  "memory": 12,
  "memory_type": "GDDR6X",
  "core_base_clock": 2520,
  "core_boost_clock": 2550,
  "effective_memory_clock": 21000,
  "memory_bus": 192,
  "interface": "PCIe 4.0 x16",
  "frame_sync": "G-Sync",
  "length": 227,
  "tdp": 225,
  "case_expansion_slot_width": 2,
  "total_slot_width": 2.5,
  "cooling": "Dual Fans Axial-tech",
  "video_outputs": {
    "hdmi_2_1": 1,
    "hdmi_2_0": 0,
    "displayport_2_1": 3,
    "displayport_2_1a": 0,
    "displayport_1_4a": 0,
    "dvi_d": 0,
    "vga": 0,
    "_id": "6778aed8cda752bef3858dff"
  },
  "color": [],
  "core_count": 7168,
  "general_product_information": {
    "amazon_sku": "B0BZTDZL7J",
    "walmart_sku": 1979629216
  }
}